{"type":"FeatureCollection","bbox":[139.370967,36.379556,139.372114,36.382233],"features":[{"type":"Feature","properties":{"name":"新清水川橋","_iconAnchor":[12,12],"_iconSize":[24,24],"_iconUrl":"symbols/Bridge.png"},"geometry":{"type":"Point","coordinates":[139.370967,36.379556]}},{"geometry":{"coordinates":[139.371097,36.380919],"type":"Point"},"properties":{"_iconSize":[24,24],"_iconUrl":"symbols/Scenic_Area.png","name":"三葉つつじ自生地","_iconAnchor":[12,12]},"type":"Feature"},{"properties":{"_iconAnchor":[12,12],"name":"三葉つつじ山","_iconUrl":"symbols/Summit.png","_iconSize":[24,24]},"geometry":{"coordinates":[139.372114,36.380481],"type":"Point"},"type":"Feature"},{"geometry":{"coordinates":[139.371933,36.382233],"type":"Point"},"properties":{"_iconUrl":"symbols/Parking_Area.png","_iconSize":[24,24],"_iconAnchor":[12,12],"name":"恵性院駐車場"},"type":"Feature"}]}
